Metadata-Version: 1.1
Name: waveshare-drivers
Version: 1.0.0
Summary: Waveshare e-Paper Display
Home-page: UNKNOWN
Author: Waveshare
Author-email: UNKNOWN
License: UNKNOWN
Download-URL: https://github.com/LeoinChina/waveshare_epd/archive/refs/tags/v1.tar.gz
Platform: UNKNOWN
